data_transformation_marta_miseke1/__init__.py
data_transformation_marta_miseke1/transformation.py
data_transformation_marta_miseke1-0.1.1a11.dist-info/METADATA
data_transformation_marta_miseke1-0.1.1a11.dist-info/WHEEL
data_transformation_marta_miseke1-0.1.1a11.dist-info/RECORD
