Metadata-Version: 2.1
Name: data-transformation-marta-miseke1
Version: 0.1.1a11
Summary: 
Author: Marta
Author-email: marta.miseke@seb.se
Requires-Python: >=3.11,<3.12
Classifier: Programming Language :: Python :: 3
Classifier: Programming Language :: Python :: 3.11
Requires-Dist: logging (>=0.4.9.6,<0.5.0.0)
Requires-Dist: numpy (>=1.26.4,<1.27.0)
Requires-Dist: pytest (>=8.2.0,<8.3.0)
